win_roboco_py.py
win_roboco_py-0.5.0.dist-info/LICENSE
win_roboco_py-0.5.0.dist-info/WHEEL
win_roboco_py-0.5.0.dist-info/METADATA
win_roboco_py-0.5.0.dist-info/RECORD
