Metadata-Version: 2.1
Name: win-roboco-py
Version: 0.5.0
Summary: A wrapper for Window's Robocopy utility.
Keywords: copy,move,filesystem,windows
Author: Emilian Cioca
Requires-Python: >=3.7
Classifier: Development Status :: 4 - Beta
Classifier: Programming Language :: Python :: 3
Classifier: License :: OSI Approved :: MIT License
Classifier: Operating System :: Microsoft
Project-URL: Bug Tracker, https://github.com/EmilianC/win-roboco-py/issues
Project-URL: Changes, https://github.com/EmilianC/win-roboco-py/blob/main/CHANGELOG.md
Project-URL: Homepage, https://github.com/EmilianC/win-roboco-py
Project-URL: Repository, https://github.com/EmilianC/win-roboco-py
